LICENSE
MANIFEST.in
README.md
requirements.txt
setup.py
cft/__init__.py
cft/main.py
cft/utils/__init__.py
cft/utils/config.py
cft/utils/constants.py
cft/utils/race.py
cft/utils/submit.py
cft/utils/test.py
cft/utils/upgrade.py
codeforces_toolbox.egg-info/PKG-INFO
codeforces_toolbox.egg-info/SOURCES.txt
codeforces_toolbox.egg-info/dependency_links.txt
codeforces_toolbox.egg-info/entry_points.txt
codeforces_toolbox.egg-info/requires.txt
codeforces_toolbox.egg-info/top_level.txt