Metadata-Version: 2.1
Name: codeforces-toolbox
Version: 1.6.3
Summary: Codeforces CLI that makes writing contests more efficient.
Home-page: https://github.com/mdbrnowski/codeforces-toolbox
Author: Michał Dobranowski
Author-email: mdbrnowski@gmail.com
License: MIT
Keywords: cli,competitive-programming,codeforces
Platform: UNKNOWN
Classifier: Development Status :: 5 - Production/Stable
Classifier: Environment :: Console
Classifier: License :: OSI Approved :: MIT License
Classifier: Operating System :: MacOS
Classifier: Operating System :: Microsoft :: Windows
Classifier: Operating System :: POSIX :: Linux
Classifier: Programming Language :: Python
Classifier: Topic :: Terminals
Requires-Python: >=3.7
License-File: LICENSE
